fnw/CACHE.json
fnw/__init__.py
fnw/fiddling_with_minfin.py
fnw/inst1.png
fnw/inst2.png
fnw/numeric.json
fnw-0.0.2.dist-info/LICENCE
fnw-0.0.2.dist-info/METADATA
fnw-0.0.2.dist-info/WHEEL
fnw-0.0.2.dist-info/top_level.txt
fnw-0.0.2.dist-info/RECORD
