Metadata-Version: 2.1
Name: fnw
Version: 0.0.2
Summary: A small library for getting info about Ukrainian banks 
Author: Solohub Illia
Author-email: illa98994@gmail.com
License: MIT
Project-URL: Source, https://github.com/Mimkaa/Fiddling_with_minfin
Keywords: python,exchange rate,minfin
Platform: UNKNOWN
Classifier: Intended Audience :: Education
Classifier: Programming Language :: Python :: 3
Classifier: License :: OSI Approved :: MIT License
Classifier: Operating System :: OS Independent
License-File: LICENCE
Requires-Dist: certifi (==2021.10.8)
Requires-Dist: chardet (==3.0.4)
Requires-Dist: charset-normalizer (==2.0.12)
Requires-Dist: cycler (==0.11.0)
Requires-Dist: fonttools (==4.33.3)
Requires-Dist: googletrans (==4.0.0rc1)
Requires-Dist: h11 (==0.9.0)
Requires-Dist: h2 (==3.2.0)
Requires-Dist: hpack (==3.0.0)
Requires-Dist: hstspreload (==2021.12.1)
Requires-Dist: httpcore (==0.9.1)
Requires-Dist: httpx (==0.13.3)
Requires-Dist: hyperframe (==5.2.0)
Requires-Dist: idna (==2.10)
Requires-Dist: kiwisolver (==1.4.2)
Requires-Dist: lxml (==4.8.0)
Requires-Dist: matplotlib (==3.5.1)
Requires-Dist: numpy (==1.22.3)
Requires-Dist: packaging (==21.3)
Requires-Dist: pandas (==1.4.2)
Requires-Dist: Pillow (==9.1.0)
Requires-Dist: pyparsing (==3.0.8)
Requires-Dist: python-dateutil (==2.8.2)
Requires-Dist: pytz (==2022.1)
Requires-Dist: requests (==2.27.1)
Requires-Dist: rfc3986 (==1.5.0)
Requires-Dist: six (==1.16.0)
Requires-Dist: sniffio (==1.2.0)
Requires-Dist: urllib3 (==1.26.9)
